{"characters":[{"agent":[{"w":"overjoyed","i":104},{"w":"done","i":963}],"NNPcount":2,"names":[{"c":2,"n":"Henry"}],"mod":[{"w":"happy","i":941}],"speaking":[],"patient":[],"g":2,"id":0,"poss":[{"w":"journey","i":967}]},{"agent":[{"w":"was","i":40},{"w":"was","i":53},{"w":"went","i":74},{"w":"sat","i":2812},{"w":"said","i":3078}],"NNPcount":3,"names":[{"c":3,"n":"Lady Bertram"}],"mod":[{"w":"able","i":2841}],"speaking":[{"w":"\" I am glad you gave him something considerable , \" ","i":3065}],"patient":[{"w":"watched","i":115}],"g":1,"id":1,"poss":[{"w":"go","i":109},{"w":"aunts","i":2851}]},{"agent":[{"w":"conferring","i":1452},{"w":"cost","i":2915},{"w":"be","i":3012},{"w":"have","i":3020},{"w":"gone","i":3112},{"w":"forget","i":3309},{"w":"goes","i":3316},{"w":"go","i":3340}],"NNPcount":17,"names":[{"c":17,"n":"William"}],"mod":[{"w":"lieutenant","i":2002},{"w":"subject","i":2785},{"w":"able","i":2891}],"speaking":[{"w":"\" cried Mrs. Norris , reddening . \" ","i":3100}],"patient":[{"w":"given","i":2945},{"w":"put","i":3041}],"g":2,"id":2,"poss":[{"w":"attachment","i":1351},{"w":"part","i":1465},{"w":"behalf","i":1485},{"w":"destination","i":2154},{"w":"promotion","i":2328},{"w":"commission","i":2791},{"w":"appointment","i":2857},{"w":"uncle","i":2906},{"w":"uncle","i":2918},{"w":"cabin","i":3007},{"w":"father","i":3032},{"w":"pockets","i":3118},{"w":"journey","i":3128},{"w":"words","i":3406},{"w":"advancement","i":4335}]},{"agent":[{"w":"receives","i":3810}],"NNPcount":2,"names":[{"c":2,"n":"Mary"}],"mod":[],"speaking":[],"patient":[{"w":"disappointed","i":3805}],"g":1,"id":3,"poss":[{"w":"note","i":3802}]},{"agent":[{"w":"continued","i":485},{"w":"apply","i":929},{"w":"meant","i":2588},{"w":"know","i":2610},{"w":"eat","i":2701},{"w":"turn","i":2746},{"w":"felt","i":2760},{"w":"join","i":2779},{"w":"thought","i":2809},{"w":"were","i":3389},{"w":"found","i":4136},{"w":"made","i":4179}],"NNPcount":9,"names":[{"c":6,"n":"Miss Crawford"},{"c":3,"n":"Crawford"}],"mod":[{"w":"distressed","i":2642},{"w":"afraid","i":2662},{"w":"ready","i":2723},{"w":"silent","i":2772}],"speaking":[{"w":"\" I will not talk of my own happiness , \" ","i":501},{"w":"\" The conclusion was scarcely intelligible from increasing fright , for she found that Mr. Crawford , under pretence of receiving the note , was coming towards her . \" ","i":4125}],"patient":[],"g":1,"id":4,"poss":[{"w":"hand","i":461},{"w":"eye","i":469},{"w":"heart","i":479},{"w":"brother","i":983},{"w":"meaning","i":2580},{"w":"brother","i":2594},{"w":"different","i":2676},{"w":"comfort","i":2690},{"w":"appetite","i":2720},{"w":"eyes","i":2749},{"w":"demerits","i":3432},{"w":"superiors","i":3468},{"w":"note","i":3897}]},{"agent":[],"NNPcount":2,"names":[{"c":2,"n":"Charles"}],"mod":[{"w":"much","i":411}],"speaking":[],"patient":[],"g":2,"id":5,"poss":[{"w":"regard","i":422}]},{"agent":[{"w":"know","i":97},{"w":"sought","i":1822},{"w":"reached","i":1873},{"w":"do","i":1929},{"w":"made","i":1939},{"w":"insulted","i":1952},{"w":"was","i":2159},{"w":"told","i":3137},{"w":"joined","i":3598},{"w":"was","i":3721},{"w":"began","i":3762}],"NNPcount":11,"names":[{"c":11,"n":"Thomas"}],"mod":[{"w":"inexcusable","i":1917},{"w":"serious","i":1977}],"speaking":[],"patient":[{"w":"heard","i":1766},{"w":"cost","i":3257}],"g":2,"id":6,"poss":[{"w":"way","i":1774},{"w":"mind","i":1808},{"w":"politeness","i":1864},{"w":"visitor","i":1883},{"w":"habits","i":1926},{"w":"turning","i":3779}]},{"agent":[{"w":"seemed","i":2866},{"w":"given","i":2942},{"w":"did","i":2947},{"w":"knew","i":3010},{"w":"reddening","i":3103},{"w":"question","i":3148},{"w":"said","i":3176},{"w":"refused","i":3737}],"NNPcount":5,"names":[{"c":4,"n":"Mrs. Norris"},{"c":1,"n":"Norris"}],"mod":[{"w":"glad","i":2937}],"speaking":[{"w":"\" Mrs. Norris , being not at all inclined to question its sufficiency , began to take the matter in another point . \" ","i":3146}],"patient":[],"g":1,"id":7,"poss":[{"w":"_","i":2932},{"w":"power","i":2962},{"w":"_","i":2985},{"w":"means","i":2990}]},{"agent":[{"w":"pray","i":1539},{"w":"talking","i":1577},{"w":"said","i":1626},{"w":"pressed","i":1653},{"w":"address","i":2036},{"w":"seen","i":2045},{"w":"think","i":2230},{"w":"was","i":2333},{"w":"had","i":2348},{"w":"spoke","i":2647},{"w":"spoke","i":2653},{"w":"talked","i":2684},{"w":"sat","i":2757},{"w":"joined","i":3601},{"w":"was","i":3617},{"w":"understood","i":4064},{"w":"dare","i":4070},{"w":"coming","i":4140},{"w":"perceiving","i":4167}],"NNPcount":13,"names":[{"c":13,"n":"Mr. Crawford"}],"mod":[{"w":"close","i":2341}],"speaking":[],"patient":[{"w":"obliged","i":1186},{"w":"engaged","i":2209},{"w":"see","i":2248}],"g":2,"id":8,"poss":[{"w":"affection","i":1584},{"w":"friendship","i":2068},{"w":"gone","i":2108},{"w":"sister","i":2355},{"w":"voice","i":2374},{"w":"voice","i":2670},{"w":"interpretation","i":2736},{"w":"_","i":2764},{"w":"manners","i":4060},{"w":"attentions","i":4399}]}],"id":"mansfield_031"}